main.py
test_pypi_donny_test-0.1.1.dist-info/METADATA
test_pypi_donny_test-0.1.1.dist-info/WHEEL
test_pypi_donny_test-0.1.1.dist-info/top_level.txt
test_pypi_donny_test-0.1.1.dist-info/RECORD
